mqt/bench/__init__.py
mqt/bench/_version.py
mqt/bench/benchmark_generation.py
mqt/bench/cli.py
mqt/bench/output.py
mqt/bench/py.typed
mqt/bench/benchmarks/__init__.py
mqt/bench/benchmarks/_registry.py
mqt/bench/benchmarks/ae.py
mqt/bench/benchmarks/bmw_quark_cardinality.py
mqt/bench/benchmarks/bmw_quark_copula.py
mqt/bench/benchmarks/bv.py
mqt/bench/benchmarks/cdkm_ripple_carry_adder.py
mqt/bench/benchmarks/dj.py
mqt/bench/benchmarks/draper_qft_adder.py
mqt/bench/benchmarks/full_adder.py
mqt/bench/benchmarks/ghz.py
mqt/bench/benchmarks/graphstate.py
mqt/bench/benchmarks/grover.py
mqt/bench/benchmarks/half_adder.py
mqt/bench/benchmarks/hhl.py
mqt/bench/benchmarks/hrs_cumulative_multiplier.py
mqt/bench/benchmarks/modular_adder.py
mqt/bench/benchmarks/multiplier.py
mqt/bench/benchmarks/qaoa.py
mqt/bench/benchmarks/qft.py
mqt/bench/benchmarks/qftentangled.py
mqt/bench/benchmarks/qnn.py
mqt/bench/benchmarks/qpeexact.py
mqt/bench/benchmarks/qpeinexact.py
mqt/bench/benchmarks/qwalk.py
mqt/bench/benchmarks/randomcircuit.py
mqt/bench/benchmarks/rg_qft_multiplier.py
mqt/bench/benchmarks/shor.py
mqt/bench/benchmarks/vbe_ripple_carry_adder.py
mqt/bench/benchmarks/vqe_real_amp.py
mqt/bench/benchmarks/vqe_su2.py
mqt/bench/benchmarks/vqe_two_local.py
mqt/bench/benchmarks/wstate.py
mqt/bench/targets/__init__.py
mqt/bench/targets/devices/__init__.py
mqt/bench/targets/devices/_registry.py
mqt/bench/targets/devices/ibm.py
mqt/bench/targets/devices/ionq.py
mqt/bench/targets/devices/iqm.py
mqt/bench/targets/devices/quantinuum.py
mqt/bench/targets/devices/rigetti.py
mqt/bench/targets/gatesets/__init__.py
mqt/bench/targets/gatesets/_registry.py
mqt/bench/targets/gatesets/clifford_t.py
mqt/bench/targets/gatesets/ibm.py
mqt/bench/targets/gatesets/ionq.py
mqt/bench/targets/gatesets/iqm.py
mqt/bench/targets/gatesets/quantinuum.py
mqt/bench/targets/gatesets/rigetti.py
mqt_bench-2.1.0.dist-info/METADATA
mqt_bench-2.1.0.dist-info/WHEEL
mqt_bench-2.1.0.dist-info/entry_points.txt
mqt_bench-2.1.0.dist-info/licenses/LICENSE.md
mqt_bench-2.1.0.dist-info/RECORD
