Metadata-Version: 2.4
Name: mqt.bench
Version: 2.1.0
Summary: MQT Bench - A MQT tool for Benchmarking Quantum Software Tools
Project-URL: Homepage, https://github.com/cda-tum/mqtbench
Project-URL: Bug Tracker, https://github.com/cda-tum/mqtbench/issues
Project-URL: Discussions, https://github.com/cda-tum/mqtbench/discussions
Project-URL: Research, https://www.cda.cit.tum.de/research/quantum/
Author-email: Nils Quetschlich <nils.quetschlich@tum.de>, Lukas Burgholzer <lukas.burgholzer@tum.de>
License-Expression: MIT
License-File: LICENSE.md
Keywords: MQT,benchmarking,performance,quantum computing,testing
Classifier: Development Status :: 4 - Beta
Classifier: Intended Audience :: Developers
Classifier: Intended Audience :: Science/Research
Classifier: Natural Language :: English
Classifier: Operating System :: MacOS
Classifier: Operating System :: Microsoft :: Windows
Classifier: Operating System :: POSIX :: Linux
Classifier: Programming Language :: Python :: 3
Classifier: Programming Language :: Python :: 3 :: Only
Classifier: Programming Language :: Python :: 3.10
Classifier: Programming Language :: Python :: 3.11
Classifier: Programming Language :: Python :: 3.12
Classifier: Programming Language :: Python :: 3.13
Classifier: Programming Language :: Python :: 3.14
Classifier: Topic :: Scientific/Engineering :: Electronic Design Automation (EDA)
Classifier: Typing :: Typed
Requires-Python: >=3.10
Requires-Dist: networkx>=2.8.8
Requires-Dist: numpy>=1.22
Requires-Dist: numpy>=1.24; python_version >= '3.11'
Requires-Dist: numpy>=1.26; python_version >= '3.12'
Requires-Dist: numpy>=2.1; python_version >= '3.13'
Requires-Dist: numpy>=2.3.2; python_version >= '3.14'
Requires-Dist: qiskit[qasm3-import]>=1.3.2
Requires-Dist: scikit-learn>=1.5.2
Requires-Dist: scikit-learn>=1.7.2; python_version >= '3.14'
